beatx/__init__.py
beatx/schedulers.py
beatx/serializer.py
beatx/utils.py
beatx/store/__init__.py
beatx/store/dummy.py
beatx/store/redis.py
celery_beatx-0.3.0.dist-info/DESCRIPTION.rst
celery_beatx-0.3.0.dist-info/METADATA
celery_beatx-0.3.0.dist-info/RECORD
celery_beatx-0.3.0.dist-info/WHEEL
celery_beatx-0.3.0.dist-info/metadata.json
celery_beatx-0.3.0.dist-info/top_level.txt
