Metadata-Version: 2.0
Name: celery-beatx
Version: 0.3.0
Summary: Adds scheduler and cluster-scheduler for celery
Home-page: https://github.com/mixkorshun/celery-beatx
Author: Vladislav Bakin
Author-email: mixkorshun@gmail.com
License: MIT
Keywords: celery,celerybeat,scheduler
Platform: UNKNOWN
Classifier: Intended Audience :: Developers
Classifier: Natural Language :: English
Classifier: License :: OSI Approved :: MIT License
Classifier: Programming Language :: Python
Classifier: Programming Language :: Python :: 3
Classifier: Programming Language :: Python :: 3.4
Classifier: Programming Language :: Python :: 3.5
Classifier: Programming Language :: Python :: 3.6
Requires-Dist: celery
